MANIFEST.in
account_test_data.xml
account_test_report.xml
account_test_view.xml
setup.py
./__init__.py
./__openerp__.py
./account_test.py
./report/__init__.py
./report/account_test_report.py
i18n/account_test.pot
i18n/ar.po
i18n/cs.po
i18n/da.po
i18n/en_GB.po
i18n/es.po
i18n/fr.po
i18n/hr.po
i18n/hu.po
i18n/it.po
i18n/mk.po
i18n/mn.po
i18n/nb.po
i18n/nl.po
i18n/pl.po
i18n/pt.po
i18n/pt_BR.po
i18n/ro.po
i18n/ru.po
i18n/sl.po
i18n/tr.po
i18n/zh_CN.po
openerp_account_test.egg-info/PKG-INFO
openerp_account_test.egg-info/SOURCES.txt
openerp_account_test.egg-info/dependency_links.txt
openerp_account_test.egg-info/requires.txt
openerp_account_test.egg-info/top_level.txt
report/account_test.rml
report/account_test.sxw
security/ir.model.access.csv